mimesis_and_ge/__init__.py
mimesis_and_ge/transformations.py
mimesis_and_ge/custom_datadir/es/file_name.json
mimesis_and_ge-0.1.0.dist-info/LICENSE
mimesis_and_ge-0.1.0.dist-info/WHEEL
mimesis_and_ge-0.1.0.dist-info/METADATA
mimesis_and_ge-0.1.0.dist-info/RECORD
