Metadata-Version: 2.1
Name: mimesis_and_ge
Version: 0.1.0
Summary: A Python module for mimesis and Great Expectations
Home-page: https://github.com/IslasGECI/mimesis_and_ge
Author: Ciencia de Datos • GECI
Author-email: ciencia.datos@islas.org.mx
Requires-Python: >=3.9
Classifier: License :: OSI Approved :: GNU General Public License v3 or later (GPLv3+)
Requires-Dist: great_expectations
Requires-Dist: mimesis
Requires-Dist: pytest-mimesis
